emailPortal/__init__.py
emailPortal/core.py
emailPortal/emailPortal/__init__.py
emailPortal/emailPortal/core.py
emailportal-0.1.1.dist-info/METADATA
emailportal-0.1.1.dist-info/WHEEL
emailportal-0.1.1.dist-info/top_level.txt
emailportal-0.1.1.dist-info/RECORD
