Metadata-Version: 2.4
Name: emailportal
Version: 0.1.1
Summary: Simple email package
Author: You
License: MIT
Requires-Python: >=3.8
